random_rhythms/__init__.py
random_rhythms/random_rhythms.py
random_rhythms-0.1.11.dist-info/licenses/LICENSE
random_rhythms-0.1.11.dist-info/METADATA
random_rhythms-0.1.11.dist-info/WHEEL
random_rhythms-0.1.11.dist-info/top_level.txt
random_rhythms-0.1.11.dist-info/RECORD
